db_mutex/__init__.py
db_mutex/apps.py
db_mutex/db_mutex.py
db_mutex/exceptions.py
db_mutex/models.py
db_mutex/version.py
db_mutex/migrations/0001_initial.py
db_mutex/migrations/__init__.py
db_mutex/tests/__init__.py
db_mutex/tests/db_mutex_tests.py
django_db_mutex-3.1.0.dist-info/LICENSE
django_db_mutex-3.1.0.dist-info/METADATA
django_db_mutex-3.1.0.dist-info/WHEEL
django_db_mutex-3.1.0.dist-info/top_level.txt
django_db_mutex-3.1.0.dist-info/RECORD
